wikidata_fast_query/__init__.py
wikidata_fast_query/dict_definition.py
wikidata_fast_query/py.typed
wikidata_fast_query-2.3.0.dist-info/LICENSE
wikidata_fast_query-2.3.0.dist-info/METADATA
wikidata_fast_query-2.3.0.dist-info/WHEEL
wikidata_fast_query-2.3.0.dist-info/top_level.txt
wikidata_fast_query-2.3.0.dist-info/zip-safe
wikidata_fast_query-2.3.0.dist-info/RECORD
